getScreenSize/__init__.py
getScreenSize/core.py
getScreenSize-0.1.1.dist-info/LICENSE
getScreenSize-0.1.1.dist-info/METADATA
getScreenSize-0.1.1.dist-info/WHEEL
getScreenSize-0.1.1.dist-info/top_level.txt
getScreenSize-0.1.1.dist-info/RECORD
