Metadata-Version: 2.1
Name: getScreenSize
Version: 0.1.1
Summary: 跨平台自动获取屏幕分辨率（Linux 自动安装依赖）
Home-page: https://github.com/Knighthood2001/Python-getScreenSize
Author: knighthood
Author-email: your@email.com
License: UNKNOWN
Platform: UNKNOWN
Classifier: Programming Language :: Python :: 3
Classifier: License :: OSI Approved :: MIT License
Classifier: Operating System :: Microsoft :: Windows
Classifier: Operating System :: POSIX :: Linux
Requires-Python: >=3.6
Requires-Dist: python3-xlib
